{
  "data": {
    "article": {},
    "attachments": {
      "media_keys": [
        "3_2068084651260882944"
      ]
    },
    "author_id": "1980612830824132609",
    "conversation_id": "2068084666024726720",
    "created_at": "2026-06-19T21:33:02.000Z",
    "edit_controls": {
      "editable_until": "2026-06-19T22:33:02.000Z",
      "edits_remaining": 5,
      "is_edit_eligible": true
    },
    "edit_history_tweet_ids": [
      "2068084666024726720"
    ],
    "entities": {
      "urls": [
        {
          "display_url": "pic.x.com/kDtrtVYaJ9",
          "end": 25,
          "expanded_url": "https://x.com/seeFvn/status/2068084666024726720/photo/1",
          "media_key": "3_2068084651260882944",
          "start": 2,
          "url": "https://t.co/kDtrtVYaJ9"
        }
      ]
    },
    "geo": {},
    "id": "2068084666024726720",
    "lang": "qme",
    "note_tweet": {
      "entities": {}
    },
    "possibly_sensitive": false,
    "public_metrics": {
      "bookmark_count": 0,
      "impression_count": 0,
      "like_count": 0,
      "quote_count": 0,
      "reply_count": 0,
      "retweet_count": 0
    },
    "reply_settings": "everyone",
    "text": "🎂 https://t.co/kDtrtVYaJ9"
  },
  "includes": {
    "media": [
      {
        "height": 2048,
        "media_key": "3_2068084651260882944",
        "public_metrics": {},
        "type": "photo",
        "url": "https://pbs.twimg.com/media/HLNQCHvXsAArFs2.jpg",
        "width": 947
      }
    ],
    "tweets": [
      {
        "article": {},
        "attachments": {
          "media_keys": [
            "3_2068084651260882944"
          ]
        },
        "author_id": "1980612830824132609",
        "conversation_id": "2068084666024726720",
        "created_at": "2026-06-19T21:33:02.000Z",
        "edit_controls": {
          "editable_until": "2026-06-19T22:33:02.000Z",
          "edits_remaining": 5,
          "is_edit_eligible": true
        },
        "edit_history_tweet_ids": [
          "2068084666024726720"
        ],
        "entities": {
          "urls": [
            {
              "display_url": "pic.x.com/kDtrtVYaJ9",
              "end": 25,
              "expanded_url": "https://x.com/seeFvn/status/2068084666024726720/photo/1",
              "media_key": "3_2068084651260882944",
              "start": 2,
              "url": "https://t.co/kDtrtVYaJ9"
            }
          ]
        },
        "geo": {},
        "id": "2068084666024726720",
        "lang": "qme",
        "note_tweet": {
          "entities": {}
        },
        "possibly_sensitive": false,
        "public_metrics": {
          "bookmark_count": 0,
          "impression_count": 0,
          "like_count": 0,
          "quote_count": 0,
          "reply_count": 0,
          "retweet_count": 0
        },
        "reply_settings": "everyone",
        "text": "🎂 https://t.co/kDtrtVYaJ9"
      }
    ],
    "users": [
      {
        "created_at": "2025-10-21T12:31:20.000Z",
        "description": "UK🇬🇧🇪🇺🇹🇼🇺🇸\nEN 学习中/國語 OK\nabuse/不太見證/药理 OK/DXM&PGB 了解深度/",
        "id": "1980612830824132609",
        "name": "foes",
        "pinned_tweet_id": "2067910349643210868",
        "profile_image_url": "https://pbs.twimg.com/profile_images/2042025344224653313/_OBGlLo3_normal.jpg",
        "protected": false,
        "public_metrics": {
          "followers_count": 545,
          "following_count": 710,
          "like_count": 4587,
          "listed_count": 0,
          "media_count": 111,
          "tweet_count": 1551
        },
        "url": "",
        "username": "seeFvn",
        "verified": true
      }
    ]
  }
}